nbchkr/__init__.py
nbchkr/__main__.py
nbchkr/checks.py
nbchkr/utils/__init__.py
nbchkr-0.0.8.dist-info/entry_points.txt
nbchkr-0.0.8.dist-info/LICENSE
nbchkr-0.0.8.dist-info/WHEEL
nbchkr-0.0.8.dist-info/METADATA
nbchkr-0.0.8.dist-info/RECORD
