Metadata-Version: 2.1
Name: nbchkr
Version: 0.0.8
Summary: A lightweight tool to grade notebook assignements
Author-email: Vince Knight <knightva@cardiff.ac.uk>
Requires-Dist: humanize
Requires-Dist: jupyter
Requires-Dist: pandas
Requires-Dist: typer
Requires-Dist: Unidecode==1.1.1
Requires-Dist: ypy-websocket<0.6.0
Requires-Dist: sphinx-rtd-theme ; extra == "docs"
Project-URL: Homepage, http://nbchkr.readthedocs.io
Provides-Extra: docs
